Metadata-Version: 1.1
Name: django-send-email
Version: 0.1.0
Summary: Send emails from the command line using Django's settings
Home-page: https://github.com/justquick/django-send-email
Author: Justin Quick
Author-email: justquick@gmail.com
License: BSD License
Platform: UNKNOWN
Classifier: Environment :: Console
Classifier: Framework :: Django
Classifier: Intended Audience :: Developers
Classifier: License :: OSI Approved :: BSD License
Classifier: Operating System :: OS Independent
Classifier: Programming Language :: Python
Classifier: Topic :: Communications :: Email
